django_bulk_lifecycle/__init__.py
django_bulk_lifecycle/conditions.py
django_bulk_lifecycle/constants.py
django_bulk_lifecycle/context.py
django_bulk_lifecycle/decorators.py
django_bulk_lifecycle/engine.py
django_bulk_lifecycle/enums.py
django_bulk_lifecycle/handler.py
django_bulk_lifecycle/manager.py
django_bulk_lifecycle/models.py
django_bulk_lifecycle/priority.py
django_bulk_lifecycle/queryset.py
django_bulk_lifecycle/registry.py
django_bulk_lifecycle-0.1.50.dist-info/LICENSE
django_bulk_lifecycle-0.1.50.dist-info/METADATA
django_bulk_lifecycle-0.1.50.dist-info/WHEEL
django_bulk_lifecycle-0.1.50.dist-info/RECORD
