Metadata-Version: 2.1
Name: django-bulk-lifecycle
Version: 0.1.50
Summary: Salesforce-style lifecycle hooks for Django bulk operations
Home-page: https://github.com/AugendLimited/django-bulk-lifecycle
License: MIT
Keywords: django,bulk,lifecycle,hooks
Author: Konrad Beck
Author-email: konrad.beck@merchantcapital.co.za
Requires-Python: >=3.11,<4.0
Classifier: License :: OSI Approved :: MIT License
Classifier: Programming Language :: Python :: 3
Classifier: Programming Language :: Python :: 3.11
Classifier: Programming Language :: Python :: 3.12
Classifier: Programming Language :: Python :: 3.13
Requires-Dist: Django (>=4.0)
Project-URL: Repository, https://github.com/AugendLimited/django-bulk-lifecycle
